vectormatrixlib/__init__.py
vectormatrixlib/matrix.py
vectormatrixlib-1.0.0.dist-info/LICENSE.txt
vectormatrixlib-1.0.0.dist-info/METADATA
vectormatrixlib-1.0.0.dist-info/WHEEL
vectormatrixlib-1.0.0.dist-info/top_level.txt
vectormatrixlib-1.0.0.dist-info/RECORD
