Metadata-Version: 2.1
Name: vectormatrixlib
Version: 1.0.0
Summary: Linear Algebra Matrix Tool
Home-page: https://github.com/andrewking1597/vector-matrix
Author: Andrew King
Author-email: andrewking1597@gmail.com
License: UNKNOWN
Platform: UNKNOWN
License-File: LICENSE.txt
